fxplan/__init__.py
fxplan/calculator.py
fxplan/calculator_base.py
fxplan/result.py
fxplan/symbol.py
fxplan/utils.py
fxplan-0.1.0.dist-info/licenses/LICENSE
fxplan-0.1.0.dist-info/METADATA
fxplan-0.1.0.dist-info/WHEEL
fxplan-0.1.0.dist-info/top_level.txt
fxplan-0.1.0.dist-info/RECORD
