Metadata-Version: 2.4
Name: fxplan
Version: 0.1.0
Summary: A comprehensive Python library for forex trading calculations, including position sizing, risk/reward analysis, stop loss and take profit calculations, and commission handling.
Author-email: LS Hung <ls@hung.vn>
License-Expression: MIT
Project-URL: Homepage, https://github.com/lshung/fxplan
Project-URL: Repository, https://github.com/lshung/fxplan
Project-URL: Issues, https://github.com/lshung/fxplan/issues
Keywords: forex,trading,calculator,position-sizing,risk-reward,fx
Classifier: Development Status :: 4 - Beta
Classifier: Intended Audience :: Financial and Insurance Industry
Classifier: Programming Language :: Python :: 3
Classifier: Programming Language :: Python :: 3.7
Classifier: Programming Language :: Python :: 3.8
Classifier: Programming Language :: Python :: 3.9
Classifier: Programming Language :: Python :: 3.10
Classifier: Programming Language :: Python :: 3.11
Classifier: Programming Language :: Python :: 3.12
Classifier: Topic :: Office/Business :: Financial :: Investment
Classifier: Operating System :: OS Independent
Requires-Python: >=3.7
License-File: LICENSE
Dynamic: license-file
